happenstance_ai/__init__.py
happenstance_ai/_base_client.py
happenstance_ai/_client.py
happenstance_ai/_compat.py
happenstance_ai/_constants.py
happenstance_ai/_exceptions.py
happenstance_ai/_files.py
happenstance_ai/_models.py
happenstance_ai/_qs.py
happenstance_ai/_resource.py
happenstance_ai/_response.py
happenstance_ai/_streaming.py
happenstance_ai/_types.py
happenstance_ai/_version.py
happenstance_ai/py.typed
happenstance_ai/_utils/__init__.py
happenstance_ai/_utils/_compat.py
happenstance_ai/_utils/_datetime_parse.py
happenstance_ai/_utils/_logs.py
happenstance_ai/_utils/_proxy.py
happenstance_ai/_utils/_reflection.py
happenstance_ai/_utils/_resources_proxy.py
happenstance_ai/_utils/_streams.py
happenstance_ai/_utils/_sync.py
happenstance_ai/_utils/_transform.py
happenstance_ai/_utils/_typing.py
happenstance_ai/_utils/_utils.py
happenstance_ai/lib/.keep
happenstance_ai/resources/__init__.py
happenstance_ai/resources/research.py
happenstance_ai/resources/usage.py
happenstance_ai/types/__init__.py
happenstance_ai/types/research_create_params.py
happenstance_ai/types/research_create_response.py
happenstance_ai/types/research_retrieve_response.py
happenstance_ai/types/usage_retrieve_response.py
happenstance_ai-0.0.2.dist-info/METADATA
happenstance_ai-0.0.2.dist-info/WHEEL
happenstance_ai-0.0.2.dist-info/licenses/LICENSE
happenstance_ai-0.0.2.dist-info/RECORD
